async_tv5/__init__.py
async_tv5/client.py
async_tv5/exceptions.py
async_tv5/models.py
async_tv5-1.0.0.dist-info/licenses/LICENSE
async_tv5-1.0.0.dist-info/METADATA
async_tv5-1.0.0.dist-info/WHEEL
async_tv5-1.0.0.dist-info/top_level.txt
async_tv5-1.0.0.dist-info/RECORD
