Metadata-Version: 2.4
Name: async-tv5
Version: 1.0.0
Summary: Async Python library for TV5 API - search, info, download videos
Author-email: fsystem88 <ivan@fsystem88.ru>
Project-URL: Homepage, https://github.com/fsystem88/async-tv5
Project-URL: Bug Reports, https://github.com/fsystem88/async-tv5/issues
Project-URL: Source, https://github.com/fsystem88/async-tv5
Keywords: tv5,async,video,download,api,russian,content
Classifier: Development Status :: 4 - Beta
Classifier: Intended Audience :: Developers
Classifier: License :: OSI Approved :: MIT License
Classifier: Operating System :: OS Independent
Classifier: Programming Language :: Python :: 3
Classifier: Programming Language :: Python :: 3.7
Classifier: Programming Language :: Python :: 3.8
Classifier: Programming Language :: Python :: 3.9
Classifier: Programming Language :: Python :: 3.10
Classifier: Programming Language :: Python :: 3.11
Requires-Python: >=3.7
License-File: LICENSE
Requires-Dist: httpx>=0.24.0
Requires-Dist: beautifulsoup4>=4.12.0
Requires-Dist: aiofiles>=23.0.0
Dynamic: license-file
